package_publishing
