Metadata-Version: 2.1
Name: package_publishing
Version: 0.2
Summary: A simple example private package
Author: Leonardo
Author-email: leonardo.h@zerak.at
Classifier: Programming Language :: Python :: 3
Classifier: License :: OSI Approved :: MIT License
Classifier: Operating System :: MacOS
Requires-Python: >=3.10
